LICENSE
MANIFEST.in
setup.py
examples/__init__.py
examples/credit_card.py
examples/encode.py
examples/ex.py
examples/no_cfg.py
examples/reuse_files.py
examples/schema.py
formv/__init__.py
formv/configuration.py
formv/exception.py
formv.egg-info/PKG-INFO
formv.egg-info/SOURCES.txt
formv.egg-info/dependency_links.txt
formv.egg-info/not-zip-safe
formv.egg-info/requires.txt
formv.egg-info/top_level.txt
formv/config/config.yaml
formv/config/files/countries.yaml
formv/config/files/currencies.yaml
formv/config/files/languages.yaml
formv/config/files/countries/USA.yaml
formv/config/files/countries/postcodes/USA.yaml
formv/config/files/countries/states/USA.yaml
formv/config/files/countries/states/postcodes/USA.yaml
formv/config/i18n/formv.pot
formv/config/i18n/test/LC_MESSAGES/formv.mo
formv/config/i18n/test/LC_MESSAGES/formv.po
formv/utils/__init__.py
formv/utils/compat.py
formv/utils/encoding.py
formv/utils/fileinfo.py
formv/utils/geodist.py
formv/utils/imaging.py
formv/utils/iterators.py
formv/validators/__init__.py
formv/validators/base.py
formv/validators/chained.py
formv/validators/compound.py
formv/validators/dates.py
formv/validators/encoders.py
formv/validators/files.py
formv/validators/geographic.py
formv/validators/network.py
formv/validators/numbers.py
formv/validators/schema.py
formv/validators/signers.py
formv/validators/strings.py
logs/formv.log
tests/__init__.py
tests/test.py
tests/config/config.yaml
tests/config/files/countries.yaml
tests/config/files/currencies.yaml
tests/config/files/languages.yaml
tests/config/files/countries/USA.yaml
tests/config/files/countries/postcodes/USA.yaml
tests/config/files/countries/states/USA.yaml
tests/config/files/countries/states/postcodes/USA.yaml
tests/config/i18n/formv.pot
tests/config/i18n/test/LC_MESSAGES/formv.mo
tests/config/i18n/test/LC_MESSAGES/formv.po
tests/files/test.csv
tests/files/test.doc
tests/files/test.gif
tests/files/test.jpg
tests/files/test.pdf
tests/files/test.png
tests/files/test.rtf
tests/files/test.tif
tests/fonts/arial.ttf
tests/fonts/tahoma.ttf
tests/fonts/verdana.ttf
tests/utils/__init__.py
tests/utils/encoding.py
tests/validators/__init__.py
