Metadata-Version: 1.1
Name: formv
Version: 0.0.6
Summary: HTML forms data validation, conversion & transformation
Home-page: UNKNOWN
Author: Adrian Cristea
Author-email: adrian.cristea@gmail.com 
License: MIT
Keywords: HTML form validation conversion transformation schema
Platform: UNKNOWN
Classifier: Development Status :: 4 - Beta
Classifier: Environment :: Web Environment
Classifier: Environment :: Other Environment
Classifier: Intended Audience :: Developers
Classifier: License :: OSI Approved :: MIT License
Classifier: Operating System :: OS Independent
Classifier: Programming Language :: Python
Classifier: Programming Language :: Python :: 2
Classifier: Programming Language :: Python :: 3
Classifier: Topic :: Internet :: WWW/HTTP :: Dynamic Content :: CGI Tools/Libraries
Classifier: Topic :: Software Development :: Libraries :: Python Modules
Classifier: Topic :: Utilities
